LICENSE.md
README.md
pyproject.toml
src/ewoksfluo/__init__.py
src/ewoksfluo/h5_subprocess.py
src/ewoksfluo/resource_utils.py
src/ewoksfluo/units.py
src/ewoksfluo.egg-info/PKG-INFO
src/ewoksfluo.egg-info/SOURCES.txt
src/ewoksfluo.egg-info/dependency_links.txt
src/ewoksfluo.egg-info/entry_points.txt
src/ewoksfluo.egg-info/requires.txt
src/ewoksfluo.egg-info/top_level.txt
src/ewoksfluo/gui/__init__.py
src/ewoksfluo/gui/data_viewer.py
src/ewoksfluo/gui/fit_widget.py
src/ewoksfluo/gui/mesh_widget.py
src/ewoksfluo/gui/pick_scans_widget.py
src/ewoksfluo/gui/serialize.py
src/ewoksfluo/gui/xrf_result_viewer.py
src/ewoksfluo/io/__init__.py
src/ewoksfluo/io/blissconcat.py
src/ewoksfluo/io/convert.py
src/ewoksfluo/io/hdf5.py
src/ewoksfluo/io/nexus.py
src/ewoksfluo/io/spec.py
src/ewoksfluo/io/types.py
src/ewoksfluo/io/zap_utils.py
src/ewoksfluo/math/__init__.py
src/ewoksfluo/math/expression.py
src/ewoksfluo/math/grid_utils.py
src/ewoksfluo/math/optimal_grid.py
src/ewoksfluo/math/pad.py
src/ewoksfluo/math/regular_grid.py
src/ewoksfluo/math/rounding.py
src/ewoksfluo/math/scan_shape.py
src/ewoksfluo/tasks/__init__.py
src/ewoksfluo/tasks/hdf5_utils.py
src/ewoksfluo/tasks/math.py
src/ewoksfluo/tasks/nexus_utils.py
src/ewoksfluo/tasks/positioner_utils.py
src/ewoksfluo/tasks/xrf_results.py
src/ewoksfluo/tasks/example_data/__init__.py
src/ewoksfluo/tasks/example_data/deadtime.py
src/ewoksfluo/tasks/example_data/ihc.png
src/ewoksfluo/tasks/example_data/monitor.py
src/ewoksfluo/tasks/example_data/scan_data.py
src/ewoksfluo/tasks/example_data/tasks.py
src/ewoksfluo/tasks/example_data/xrf_spectra.py
src/ewoksfluo/tasks/fit/__init__.py
src/ewoksfluo/tasks/fit/execute.py
src/ewoksfluo/tasks/fit/tasks.py
src/ewoksfluo/tasks/input/__init__.py
src/ewoksfluo/tasks/input/concat_bliss.py
src/ewoksfluo/tasks/input/pick_scan.py
src/ewoksfluo/tasks/input/pick_scans.py
src/ewoksfluo/tasks/input/spec_to_bliss.py
src/ewoksfluo/tasks/normalization/__init__.py
src/ewoksfluo/tasks/normalization/norm_results.py
src/ewoksfluo/tasks/normalization/norm_results_stack.py
src/ewoksfluo/tasks/normalization/norm_utils.py
src/ewoksfluo/tasks/raw_counters/__init__.py
src/ewoksfluo/tasks/raw_counters/extract_counters.py
