Metadata-Version: 2.4
Name: ewoksfluo
Version: 0.6.0
Summary: Data processing workflows for X-ray Fluorescence
Author-email: ESRF <dau-pydev@esrf.fr>
License: # MIT License
Project-URL: Homepage, https://gitlab.esrf.fr/workflow/ewoksapps/ewoksfluo/
Project-URL: Documentation, https://ewoksfluo.readthedocs.io/
Project-URL: Repository, https://gitlab.esrf.fr/workflow/ewoksapps/ewoksfluo/
Project-URL: Issues, https://gitlab.esrf.fr/workflow/ewoksapps/ewoksfluo/issues
Project-URL: Changelog, https://gitlab.esrf.fr/workflow/ewoksapps/ewoksfluo/-/blob/main/CHANGELOG.md
Keywords: orange3 add-on,ewoks
Classifier: Intended Audience :: Science/Research
Classifier: License :: OSI Approved :: MIT License
Classifier: Programming Language :: Python :: 3
Requires-Python: >=3.8
License-File: LICENSE.md
Requires-Dist: ewoks[orange]
Requires-Dist: h5py
Requires-Dist: numpy
Requires-Dist: pymca>=5.8.9; python_version >= "3.9"
Requires-Dist: pymca<5.9.4,>=5.8.9; python_version < "3.9"
Requires-Dist: fabio
Requires-Dist: scipy
Requires-Dist: imageio
Requires-Dist: ewoksdata>=0.2.7
Requires-Dist: ewoksorange>=0.7.0rc0
Requires-Dist: pint
Requires-Dist: silx>=2.2
Requires-Dist: scikit-learn
Requires-Dist: psutil
Provides-Extra: test
Requires-Dist: pytest>=7; extra == "test"
Requires-Dist: pyqt5; extra == "test"
Requires-Dist: importlib_resources; python_version < "3.9" and extra == "test"
Requires-Dist: psutil; extra == "test"
Provides-Extra: dev
Requires-Dist: ewoksfluo[test]; extra == "dev"
Requires-Dist: black>=25; extra == "dev"
Requires-Dist: flake8>=4; extra == "dev"
Requires-Dist: pre-commit; extra == "dev"
Provides-Extra: doc
Requires-Dist: ewoksfluo[test]; extra == "doc"
Requires-Dist: sphinx>=4.5; extra == "doc"
Requires-Dist: sphinx-autodoc-typehints>=1.16; extra == "doc"
Requires-Dist: pydata_sphinx_theme<0.15; extra == "doc"
Dynamic: license-file
